pymd_frontmatter/__init__.py
tests/test.py
pymd_frontmatter-0.0.35.dist-info/LICENSE
pymd_frontmatter-0.0.35.dist-info/METADATA
pymd_frontmatter-0.0.35.dist-info/WHEEL
pymd_frontmatter-0.0.35.dist-info/entry_points.txt
pymd_frontmatter-0.0.35.dist-info/top_level.txt
pymd_frontmatter-0.0.35.dist-info/RECORD
